fstumbler/__init__.py
fstumbler/core.py
fstumbler/main.py
fstumbler/node.py
fstumbler/util.py
fstumbler-1.1.0.dist-info/LICENSE
fstumbler-1.1.0.dist-info/METADATA
fstumbler-1.1.0.dist-info/WHEEL
fstumbler-1.1.0.dist-info/top_level.txt
fstumbler-1.1.0.dist-info/RECORD
