Metadata-Version: 2.1
Name: fstumbler
Version: 1.1.0
Summary: The filesystem is a linked list!
Author-email: "F. Y. BALABAN" <fyb@fybx.dev>
Project-URL: homepage, https://github.com/fybx/fstumbler
Project-URL: issues, https://github.com/fybx/fstumbler/issues
Classifier: Development Status :: 4 - Beta
Classifier: Programming Language :: Python :: 3
Classifier: License :: OSI Approved :: GNU Lesser General Public License v2 or later (LGPLv2+)
Classifier: Operating System :: OS Independent
Classifier: Topic :: System :: Filesystems
Classifier: Typing :: Typed
Requires-Python: >3.7
License-File: LICENSE
